roex_python/__init__.py
roex_python/client.py
roex_python/utils.py
roex_python/controllers/__init__.py
roex_python/controllers/analysis_controller.py
roex_python/controllers/audio_cleanup_controller.py
roex_python/controllers/enhance_controller.py
roex_python/controllers/mastering_controller.py
roex_python/controllers/mix_controller.py
roex_python/controllers/upload_controller.py
roex_python/models/__init__.py
roex_python/models/analysis.py
roex_python/models/audio_cleanup.py
roex_python/models/common.py
roex_python/models/enhance.py
roex_python/models/mastering.py
roex_python/models/mixing.py
roex_python/models/upload.py
roex_python/providers/__init__.py
roex_python/providers/api_provider.py
roex_python-1.2.1.dist-info/METADATA
roex_python-1.2.1.dist-info/WHEEL
roex_python-1.2.1.dist-info/top_level.txt
roex_python-1.2.1.dist-info/RECORD
