Metadata-Version: 2.1
Name: roex_python
Version: 1.2.1
Summary: Pip package for the RoEx Tonn API
Home-page: https://github.com/roexaudio/roex-python
Author: RoEx Audio
Author-email: RoEx Audio <support@roexaudio.com>
License: MIT
Project-URL: Homepage, https://github.com/roexaudio/roex-python
Project-URL: Documentation, https://roex.stoplight.io/
Project-URL: Repository, https://github.com/roexaudio/roex-python
Project-URL: Bug Tracker, https://github.com/roexaudio/roex-python/issues
Classifier: Development Status :: 4 - Beta
Classifier: Intended Audience :: Developers
Classifier: Topic :: Multimedia :: Sound/Audio
Classifier: Topic :: Software Development :: Libraries :: Python Modules
Classifier: Programming Language :: Python :: 3
Classifier: Programming Language :: Python :: 3.7
Classifier: Programming Language :: Python :: 3.8
Classifier: Programming Language :: Python :: 3.9
Classifier: Programming Language :: Python :: 3.10
Classifier: Programming Language :: Python :: 3.11
Classifier: License :: OSI Approved :: MIT License
Classifier: Operating System :: OS Independent
Requires-Python: >=3.7
Requires-Dist: requests>=2.25.0
Provides-Extra: dev
Requires-Dist: pytest>=7.0.0; extra == "dev"
Requires-Dist: pytest-cov>=4.0.0; extra == "dev"
Requires-Dist: pytest-mock>=3.10.0; extra == "dev"
Requires-Dist: requests-mock>=1.9.3; extra == "dev"
